drlkit/__init__.py
drlkit/example.py
drlkit/main.py
drlkit/agents/TorchAgent.py
drlkit/agents/__init__.py
drlkit/environments/__init__.py
drlkit/environments/wrapper.py
drlkit/models/__init__.py
drlkit/models/LunarLander-v2/__init__.py
drlkit/networks/__init__.py
drlkit/networks/pytorch/DQN.py
drlkit/networks/pytorch/__init__.py
drlkit/utils/__init__.py
drlkit/utils/exceptions.py
drlkit/utils/memory.py
drlkit/utils/plot.py
drlkit/utils/preprocess.py
drlkit-0.1.7.dist-info/LICENSE.txt
drlkit-0.1.7.dist-info/METADATA
drlkit-0.1.7.dist-info/WHEEL
drlkit-0.1.7.dist-info/top_level.txt
drlkit-0.1.7.dist-info/RECORD
